YUyG.v
//Gleezell Vina A. Uy S14

/*
CONVERSION SOLUTION: 
(AB' + A'B)(C + D')
AB'C + AB'D' + A'BC + A'BD'
AB'C(D+D') + AB'D'(C+C') + A'BC(D+D') + A'BD'(C+C')
AB'CD + AB'CD' + AB'CD' + AB'C'D' + A'BCD + A'BCD' + A'BCD' + A'BC'D'
AB'CD + AB'CD' + AB'C'D' + A'BCD + A'BCD' + A'BC'D'
1011 + 1010 + 1000 + 0111 + 0110 + 0100
11, 10, 8, 7, 6, 4

Em=(4,6,7,8,10,11)
*/

`timescale 1ns / 1ps

//Module name: 
//F = (AB' + A'B)(C + D')

//implement negative output
module YUyG(En, F, A, B, C, D);
    input En, A, B, C, D;
    output reg F;
    wire E0, E1, E2, E3, O0, O1, O2, O3, O4, O5, O6, O7, O8, O9, O10, O11, O12, O13, O14, O15;
    wire temp1, temp2, temp3, temp4, temp5, temp6;

    // Structural decoder instantiation
    decoder_2x4 G1(En, A, B, E0, E1, E2, E3);
    decoder_2x4 G2(E0, C, D, O0, O1, O2, O3);
    decoder_2x4 G3(E1, C, D, O4, O5, O6, O7);
    decoder_2x4 G4(E2, C, D, O8, O9, O10, O11);
    decoder_2x4 G5(E3, C, D, O12, O13, O14, O15);

    //balance maxterms before nand
    not_6 G7(temp1, temp2, temp3, temp4, temp5, temp6, O4, O6, O7, O8, O10, O11);

    //nand
    always @*
    begin
        if (En == 1)
            F = ~(temp1 & temp2 & temp3 & temp4 & temp5 & temp6);
        else
            F = 1'bZ; // Set F to high-impedance ('z)
    end
endmodule

module not_6(F1, F2, F3, F4, F5, F6, O1, O2, O3, O4, O5, O6);
    input O1, O2, O3, O4, O5, O6;
    output F1, F2, F3, F4, F5, F6;

    not G6(F1, O1);
    not G7(F2, O2);
    not G8(F3, O3);
    not G9(F4, O4);
    not G10(F5, O5);
    not G11(F6, O6);

endmodule

module decoder_2x4(E,I0, I1, O0, O1, O2, O3);
    // declare input and output ports
    input E, I0, I1;
    output O0, O1, O2, O3;

    // assign output value by referring to logic diagram
    assign O0 = (E& ~I0& ~I1);
    assign O1 = (E& ~I0& I1);
    assign O2 = (E& I0& ~I1);
    assign O3 = (E& I0& I1);

endmodule

YUyG_tb.v
`timescale 1ns / 1ps

module YUyG_tb();
    wire t_F;
    reg [3:0] t_input;
    reg t_en;
    integer i;    
    
    YUyG dut(t_en, t_F, t_input[3], t_input[2], t_input[1], t_input[0]);
    initial 
    begin
        t_input = 4'b0000;
        t_en = 1'b1; // Set en to 1 initially
        for (i = 1; i < 17; i++)
            #10 t_input = i;
        
        // Set en to 0 for another round of testing
        #10 t_en = 1'b0;
        for (i = 1; i < 17; i++)
            #10 t_input = i;
    end

    initial
    begin
        $display("Written by Gleezell Vina A. Uy");
        $display("F = (AB' + A'B)(C + D')");
        $display("Verilog Model: Structural 2x4 negative output, positive enable decoder");
        $monitor("en=%b time = %0d ", t_en, $time, "ABCD = %b%b%b%b output_F = %b", t_input[3], t_input[2], t_input[1], t_input[0], t_F);
        $dumpfile("YUyG.vcd");
        $dumpvars();
    end
endmodule

YUyG.vcd
$date
	Fri Jul 21 02:03:45 2023
$end
$version
	Icarus Verilog
$end
$timescale
	1ps
$end
$scope module YUyG_tb $end
$var wire 1 ! t_F $end
$var reg 1 " t_en $end
$var reg 4 # t_input [3:0] $end
$var integer 32 $ i [31:0] $end
$scope module dut $end
$var wire 1 % A $end
$var wire 1 & B $end
$var wire 1 ' C $end
$var wire 1 ( D $end
$var wire 1 " En $end
$var wire 1 ) temp6 $end
$var wire 1 * temp5 $end
$var wire 1 + temp4 $end
$var wire 1 , temp3 $end
$var wire 1 - temp2 $end
$var wire 1 . temp1 $end
$var wire 1 / O9 $end
$var wire 1 0 O8 $end
$var wire 1 1 O7 $end
$var wire 1 2 O6 $end
$var wire 1 3 O5 $end
$var wire 1 4 O4 $end
$var wire 1 5 O3 $end
$var wire 1 6 O2 $end
$var wire 1 7 O15 $end
$var wire 1 8 O14 $end
$var wire 1 9 O13 $end
$var wire 1 : O12 $end
$var wire 1 ; O11 $end
$var wire 1 < O10 $end
$var wire 1 = O1 $end
$var wire 1 > O0 $end
$var wire 1 ? E3 $end
$var wire 1 @ E2 $end
$var wire 1 A E1 $end
$var wire 1 B E0 $end
$var reg 1 ! F $end
$scope module G1 $end
$var wire 1 " E $end
$var wire 1 % I0 $end
$var wire 1 & I1 $end
$var wire 1 B O0 $end
$var wire 1 A O1 $end
$var wire 1 @ O2 $end
$var wire 1 ? O3 $end
$upscope $end
$scope module G2 $end
$var wire 1 B E $end
$var wire 1 ' I0 $end
$var wire 1 ( I1 $end
$var wire 1 > O0 $end
$var wire 1 = O1 $end
$var wire 1 6 O2 $end
$var wire 1 5 O3 $end
$upscope $end
$scope module G3 $end
$var wire 1 A E $end
$var wire 1 ' I0 $end
$var wire 1 ( I1 $end
$var wire 1 4 O0 $end
$var wire 1 3 O1 $end
$var wire 1 2 O2 $end
$var wire 1 1 O3 $end
$upscope $end
$scope module G4 $end
$var wire 1 @ E $end
$var wire 1 ' I0 $end
$var wire 1 ( I1 $end
$var wire 1 0 O0 $end
$var wire 1 / O1 $end
$var wire 1 < O2 $end
$var wire 1 ; O3 $end
$upscope $end
$scope module G5 $end
$var wire 1 ? E $end
$var wire 1 ' I0 $end
$var wire 1 ( I1 $end
$var wire 1 : O0 $end
$var wire 1 9 O1 $end
$var wire 1 8 O2 $end
$var wire 1 7 O3 $end
$upscope $end
$scope module G7 $end
$var wire 1 . F1 $end
$var wire 1 - F2 $end
$var wire 1 , F3 $end
$var wire 1 + F4 $end
$var wire 1 * F5 $end
$var wire 1 ) F6 $end
$var wire 1 4 O1 $end
$var wire 1 2 O2 $end
$var wire 1 1 O3 $end
$var wire 1 0 O4 $end
$var wire 1 < O5 $end
$var wire 1 ; O6 $end
$upscope $end
$upscope $end
$upscope $end
$enddefinitions $end
$comment Show the parameter values. $end
$dumpall
$end
#0
$dumpvars
1B
0A
0@
0?
1>
0=
0<
0;
0:
09
08
07
06
05
04
03
02
01
00
0/
1.
1-
1,
1+
1*
1)
0(
0'
0&
0%
b1 $
b0 #
1"
0!
$end
#10000
0>
1=
1(
b10 $
b1 #
#20000
0>
16
0=
1'
0(
b11 $
b10 #
#30000
06
15
1(
b100 $
b11 #
#40000
1!
0.
0>
14
0B
1A
05
1&
0'
0(
b101 $
b100 #
#50000
0!
1.
04
13
1(
b110 $
b101 #
#60000
1!
1.
0-
04
12
03
1'
0(
b111 $
b110 #
#70000
1-
02
0,
11
1(
b1000 $
b111 #
#80000
0+
0>
10
1!
0B
1@
1,
0A
01
1%
0&
0'
0(
b1001 $
b1000 #
#90000
0!
1+
00
1/
1(
b1010 $
b1001 #
#100000
1!
1+
0*
00
1<
0/
1'
0(
b1011 $
b1010 #
#110000
1*
0<
0)
1;
1(
b1100 $
b1011 #
#120000
1+
00
1:
0!
0@
1)
1?
0;
1&
0'
0(
b1101 $
b1100 #
#130000
0:
19
1(
b1110 $
b1101 #
#140000
0:
18
09
1'
0(
b1111 $
b1110 #
#150000
08
17
1(
b10000 $
b1111 #
#160000
1>
1B
0?
07
0%
0&
0'
0(
b10001 $
b0 #
#170000
0>
0B
z!
b1 $
0"
#180000
1(
b10 $
b1 #
#190000
1'
0(
b11 $
b10 #
#200000
1(
b100 $
b11 #
#210000
1&
0'
0(
b101 $
b100 #
#220000
1(
b110 $
b101 #
#230000
1'
0(
b111 $
b110 #
#240000
1(
b1000 $
b111 #
#250000
1%
0&
0'
0(
b1001 $
b1000 #
#260000
1(
b1010 $
b1001 #
#270000
1'
0(
b1011 $
b1010 #
#280000
1(
b1100 $
b1011 #
#290000
1&
0'
0(
b1101 $
b1100 #
#300000
1(
b1110 $
b1101 #
#310000
1'
0(
b1111 $
b1110 #
#320000
1(
b10000 $
b1111 #
#330000
0%
0&
0'
0(
b10001 $
b0 #
